tutorprint_course_certificates/__about__.py
tutorprint_course_certificates/__init__.py
tutorprint_course_certificates/plugin.py
tutorprint_course_certificates/patches/.gitignore
tutorprint_course_certificates/patches/caddyfile
tutorprint_course_certificates/patches/k8s-deployments
tutorprint_course_certificates/patches/k8s-services
tutorprint_course_certificates/patches/kustomization-configmapgenerator
tutorprint_course_certificates/patches/local-docker-compose-dev-services
tutorprint_course_certificates/patches/local-docker-compose-services
tutorprint_course_certificates/patches/print-course-certificates-base-docker-compose-services
tutorprint_course_certificates/templates/print-course-certificates/apps/.gitignore
tutorprint_course_certificates/templates/print-course-certificates/apps/config.yml
tutorprint_course_certificates/templates/print-course-certificates/build/.gitignore
tutorprint_course_certificates/templates/print-course-certificates/tasks/lms/.gitignore
tutor_contrib_print_course_certificates-20.0.1.dist-info/LICENSE.txt
tutor_contrib_print_course_certificates-20.0.1.dist-info/METADATA
tutor_contrib_print_course_certificates-20.0.1.dist-info/WHEEL
tutor_contrib_print_course_certificates-20.0.1.dist-info/entry_points.txt
tutor_contrib_print_course_certificates-20.0.1.dist-info/top_level.txt
tutor_contrib_print_course_certificates-20.0.1.dist-info/RECORD
