Metadata-Version: 2.1
Name: tutor-contrib-print-course-certificates
Version: 20.0.1
Summary: Installs the nau-course-certificate project that allows to ser
Home-page: https://github.com/fccn/tutor-contrib-print-course-certificates
Author: Ivo Branco
Author-email: ivo.branco@fccn.pt
License: AGPLv3
Project-URL: Code, https://github.com/fccn/tutor-contrib-print-course-certificates
Project-URL: Issue tracker, https://github.com/fccn/tutor-contrib-print-course-certificates/issues
Classifier: Development Status :: 3 - Alpha
Classifier: Intended Audience :: Developers
Classifier: License :: OSI Approved :: GNU Affero General Public License v3
Classifier: Operating System :: OS Independent
Classifier: Programming Language :: Python
Classifier: Programming Language :: Python :: 3.8
Classifier: Programming Language :: Python :: 3.9
Classifier: Programming Language :: Python :: 3.10
Classifier: Programming Language :: Python :: 3.11
Classifier: Programming Language :: Python :: 3.12
Requires-Python: >=3.8
License-File: LICENSE.txt
Requires-Dist: tutor<21.0.0,>=20.0.0
Provides-Extra: dev
Requires-Dist: tutor[dev]<21.0.0,>=20.0.0; extra == "dev"
